schedule_convert/__init__.py
schedule_convert/landing.py
schedule_convert/landing_template.html
schedule_convert/run.py
schedule_convert/exporters/__init__.py
schedule_convert/exporters/frab_xml.py
schedule_convert/exporters/ical.py
schedule_convert/exporters/xcal.py
schedule_convert/importers/__init__.py
schedule_convert/importers/conf_data.py
schedule_convert/importers/csv.py
schedule_convert/importers/frab_xml.py
schedule_convert/importers/sessionize_json.py
schedule_convert/model/__init__.py
schedule_convert/model/event.py
schedule_convert/model/schedule.py
schedule_convert/model/simpletz.py
schedule_convert/model/speaker.py
schedule_convert-1.0.0.dist-info/LICENSE
schedule_convert-1.0.0.dist-info/METADATA
schedule_convert-1.0.0.dist-info/WHEEL
schedule_convert-1.0.0.dist-info/entry_points.txt
schedule_convert-1.0.0.dist-info/top_level.txt
schedule_convert-1.0.0.dist-info/RECORD
