Metadata-Version: 2.1
Name: schedule-convert
Version: 1.0.0
Summary: Converts and merges conference schedules, frab-compatible
Home-page: https://github.com/Zverik/schedule-convert
Author: Ilya Zverev
Author-email: ilya@zverev.info
License: MIT License
Platform: UNKNOWN
Classifier: Development Status :: 4 - Beta
Classifier: Environment :: Console
Classifier: Intended Audience :: Information Technology
Classifier: Natural Language :: English
Classifier: Operating System :: OS Independent
Classifier: Topic :: Utilities
Classifier: License :: OSI Approved :: MIT License
Classifier: Programming Language :: Python :: 3 :: Only
Requires-Python: >=3.5
Requires-Dist: vobject
Requires-Dist: qrcode[pil]
Requires-Dist: python-slugify
